freemail/__init__.py
freemail/update
freemail/data/disposable.txt
freemail/data/free.txt
freemail-1.2.17.dist-info/DESCRIPTION.rst
freemail-1.2.17.dist-info/METADATA
freemail-1.2.17.dist-info/RECORD
freemail-1.2.17.dist-info/WHEEL
freemail-1.2.17.dist-info/metadata.json
freemail-1.2.17.dist-info/top_level.txt
