Metadata-Version: 2.0
Name: freemail
Version: 1.2.17
Summary: A database of free and disposable email domains
Home-page: https://github.com/wearespindle/freemail
Author: Devhouse Spindle
Author-email: info@wearespindle.com
License: UNKNOWN
Download-URL: https://github.com/wearespindle/freemail
Keywords: email
Platform: UNKNOWN
Classifier: Development Status :: 4 - Beta
Classifier: Intended Audience :: Developers
Classifier: Programming Language :: Python :: 2.7
Classifier: Programming Language :: Python :: 3.4
Requires-Dist: tldextract
